LICENSE
MANIFEST.in
README.rst
setup.py
TkWebPage/ChromiumBrowser.py
TkWebPage/IEBrowser.py
TkWebPage/__init__.py
TkWebPage/miniblink_x64.dll
TkWebPage/node.dll
TkWebPage/test.py
TkWebPage.egg-info/PKG-INFO
TkWebPage.egg-info/SOURCES.txt
TkWebPage.egg-info/dependency_links.txt
TkWebPage.egg-info/requires.txt
TkWebPage.egg-info/top_level.txt