Metadata-Version: 1.2
Name: TkWebPage
Version: 1.2.20
Summary: 一个提供多种内核的网页浏览器|A two-kernel-webbrowser module
Home-page: https://pypi.org/
Author: CharlesCai
Author-email: 18222159844@163.com
Maintainer: 蔡沐含
Maintainer-email: c6661366613@qq.com
License: MIT License
Platform: all
Classifier: Development Status :: 4 - Beta
Classifier: Operating System :: OS Independent
Classifier: Intended Audience :: Developers
Classifier: License :: OSI Approved :: MIT License
Classifier: Programming Language :: Python
Classifier: Programming Language :: Python :: Implementation
Classifier: Programming Language :: Python :: 3
Classifier: Topic :: Software Development :: Libraries
Requires-Python: >=3
